{
"AN": {
"N": "tweens",
"SN": "color_transform_boxes",
"TL": {
"L": [
{
"LN": "Layer_1",
"FR": [
{
"I": 0,
"DU": 1,
"E": [
{
"SI": {
"SN": "color_transform_test",
"IN": "InstName",
"BM": {
"N": "0000",
"POS": {
"x": 0,
"y": 0
}
},
"ST": "G",
"FF": 0,
"LP": "LP",
"TRP": {
"x": 48.55,
"y": 48.55
},
"M3D": {
"m00": 0.263519,
"m01": 0,
"m02": 0,
"m03": 0,
"m10": 0,
"m11": 0.263519,
"m12": 0,
"m13": 0,
"m20": 0,
"m21": 0,
"m22": 1,
"m23": 0,
"m30": 0,
"m31": 0,
"m32": 0,
"m33": 1
}
}
},
{
"SI": {
"SN": "color_transform_test",
"IN": "InstName",
"BM": {
"N": "0000",
"POS": {
"x": 0,
"y": 0
}
},
"ST": "G",
"FF": 0,
"LP": "LP",
"TRP": {
"x": 48.75,
"y": 48.55
},
"M3D": {
"m00": 0.263519,
"m01": 0,
"m02": 0,
"m03": 0,
"m10": 0,
"m11": 0.263519,
"m12": 0,
"m13": 0,
"m20": 0,
"m21": 0,
"m22": 1,
"m23": 0,
"m30": 34.2,
"m31": 0,
"m32": 0,
"m33": 1
},
"C": {
"M": "CBRT",
"BRT": -0.4
}
}
},
{
"SI": {
"SN": "color_transform_test",
"IN": "InstName",
"BM": {
"N": "0000",
"POS": {
"x": 0,
"y": 0
}
},
"ST": "G",
"FF": 0,
"LP": "LP",
"TRP": {
"x": 48.75,
"y": 48.55
},
"M3D": {
"m00": 0.263519,
"m01": 0,
"m02": 0,
"m03": 0,
"m10": 0,
"m11": 0.263519,
"m12": 0,
"m13": 0,
"m20": 0,
"m21": 0,
"m22": 1,
"m23": 0,
"m30": 67.4,
"m31": 0,
"m32": 0,
"m33": 1
},
"C": {
"M": "T",
"TC": "#6600FF",
"TM": 0.55
}
}
},
{
"SI": {
"SN": "color_transform_test",
"IN": "InstName",
"BM": {
"N": "0000",
"POS": {
"x": 0,
"y": 0
}
},
"ST": "G",
"FF": 0,
"LP": "LP",
"TRP": {
"x": 48.75,
"y": 48.55
},
"M3D": {
"m00": 0.263519,
"m01": 0,
"m02": 0,
"m03": 0,
"m10": 0,
"m11": 0.263519,
"m12": 0,
"m13": 0,
"m20": 0,
"m21": 0,
"m22": 1,
"m23": 0,
"m30": 100.35,
"m31": 0,
"m32": 0,
"m33": 1
},
"C": {
"M": "CA",
"AM": 0.199219
}
}
},
{
"SI": {
"SN": "color_transform_test",
"IN": "InstName",
"BM": {
"N": "0000",
"POS": {
"x": 0,
"y": 0
}
},
"ST": "G",
"FF": 0,
"LP": "LP",
"TRP": {
"x": 48.75,
"y": 48.55
},
"M3D": {
"m00": 0.263519,
"m01": 0,
"m02": 0,
"m03": 0,
"m10": 0,
"m11": 0.263519,
"m12": 0,
"m13": 0,
"m20": 0,
"m21": 0,
"m22": 1,
"m23": 0,
"m30": 133.55,
"m31": 0,
"m32": 0,
"m33": 1
},
"C": {
"M": "AD",
"RM": 0.199219,
"GM": 0.300781,
"BM": 0.398438,
"AM": 0.101563,
"RO": 60,
"GO": 70,
"BO": 80,
"AO": 50
}
}
},
{
"SI": {
"SN": "color_transform_test",
"IN": "InstName",
"BM": {
"N": "0000",
"POS": {
"x": 0,
"y": 0
}
},
"ST": "G",
"FF": 0,
"LP": "LP",
"TRP": {
"x": 48.75,
"y": 48.55
},
"M3D": {
"m00": 0.263519,
"m01": 0,
"m02": 0,
"m03": 0,
"m10": 0,
"m11": 0.263519,
"m12": 0,
"m13": 0,
"m20": 0,
"m21": 0,
"m22": 1,
"m23": 0,
"m30": 201.25,
"m31": 0,
"m32": 0,
"m33": 1
},
"C": {
"M": "AD",
"RM": 1,
"GM": 0,
"BM": 1,
"AM": 1,
"RO": 0,
"GO": 0,
"BO": 0,
"AO": 0
}
}
},
{
"SI": {
"SN": "color_transform_test",
"IN": "InstName",
"BM": {
"N": "0000",
"POS": {
"x": 0,
"y": 0
}
},
"ST": "G",
"FF": 0,
"LP": "LP",
"TRP": {
"x": 48.55,
"y": 48.55
},
"M3D": {
"m00": 0.263519,
"m01": 0,
"m02": 0,
"m03": 0,
"m10": 0,
"m11": 0.263519,
"m12": 0,
"m13": 0,
"m20": 0,
"m21": 0,
"m22": 1,
"m23": 0,
"m30": 168.85,
"m31": 0,
"m32": 0,
"m33": 1
},
"C": {
"M": "AD",
"RM": 1,
"GM": 0,
"BM": 0,
"AM": 1,
"RO": 0,
"GO": 0,
"BO": 0,
"AO": 0
}
}
}
]
}
]
}
]
}
},
"SD": {
"S": []
},
"MD": {
"FRT": 60
}
}