{"L":[
{
"LN":"kid",
"FR":[
{
"I":0,
"DU":2,
"E":[
{"ASI":{
"MX":[1,0,0,1,4.95,-18.15],
"N":"505"
}}]},{
"I":2,
"DU":2,
"E":[
{"ASI":{
"MX":[1,0,0,1,21.15,-7],
"N":"506"
}}]},{
"I":4,
"DU":3,
"E":[
{"ASI":{
"MX":[1,0,0,1,21.6,-6.1],
"N":"507"
}}]},{
"I":7,
"DU":3,
"E":[
{"ASI":{
"MX":[1,0,0,1,21.75,-11.75],
"N":"508"
}}]},{
"I":10,
"DU":3,
"E":[
{"ASI":{
"MX":[1,0,0,1,26.95,-11],
"N":"509"
}}]},{
"I":13,
"DU":83,
"E":[
{"ASI":{
"MX":[1,0,0,1,25.2,-16.1],
"N":"510"
}}]},{
"I":96,
"DU":1,
"E":[]
}
]},{
"LN":"Layer 3",
"FR":[
{
"I":0,
"DU":2,
"E":[
{"ASI":{
"MX":[1,0,0,1,-294,110.45],
"N":"511"
}}]},{
"I":2,
"DU":3,
"E":[
{"ASI":{
"MX":[1,0,0,1,-293.2,113.2],
"N":"512"
}}]},{
"I":5,
"DU":91,
"E":[
{"ASI":{
"MX":[1,0,0,1,-292.25,113.55],
"N":"513"
}}]},{
"I":96,
"DU":1,
"E":[]
}
]},{
"LN":"Layer 4",
"FR":[
{
"I":0,
"DU":97,
"E":[
{"ASI":{
"MX":[1,0,0,1,-399.4,-454.85],
"N":"514"
}}]}
]}
]}